{
  "generated_at_utc": "2026-02-11T05:18:21.556112",
  "generated_at_ist": "2026-02-11T10:51:40.080805",
  "google_trends": [],
  "results": [
    {
      "Symbol": "KSHITIJPOL",
      "PrevClose": 2.72,
      "OpenPrice": 3.26,
      "%ChangePreOpen": 19.85,
      "Matched": false,
      "LTP": 3.07,
      "Volume": null,
      "%FromOpen": -5.83
    },
    {
      "Symbol": "GULPOLY",
      "PrevClose": 145.44,
      "OpenPrice": 169.8,
      "%ChangePreOpen": 16.75,
      "Matched": false,
      "LTP": 164.9,
      "Volume": null,
      "%FromOpen": -2.89
    },
    {
      "Symbol": "KCEIL",
      "PrevClose": 135.9,
      "OpenPrice": 153.8,
      "%ChangePreOpen": 13.17,
      "Matched": false,
      "LTP": 144.45,
      "Volume": null,
      "%FromOpen": -6.08
    },
    {
      "Symbol": "ASHIANA",
      "PrevClose": 301.85,
      "OpenPrice": 340.0,
      "%ChangePreOpen": 12.64,
      "Matched": false,
      "LTP": 344,
      "Volume": null,
      "%FromOpen": 1.18
    },
    {
      "Symbol": "JITFINFRA",
      "PrevClose": 308.65,
      "OpenPrice": 339.5,
      "%ChangePreOpen": 10.0,
      "Matched": false,
      "LTP": 339.5,
      "Volume": null,
      "%FromOpen": 0.0
    },
    {
      "Symbol": "DCMFINSERV",
      "PrevClose": 4.52,
      "OpenPrice": 4.89,
      "%ChangePreOpen": 8.19,
      "Matched": false,
      "LTP": 4.55,
      "Volume": null,
      "%FromOpen": -6.95
    },
    {
      "Symbol": "ARENTERP",
      "PrevClose": 41.71,
      "OpenPrice": 45.0,
      "%ChangePreOpen": 7.89,
      "Matched": false,
      "LTP": 42.98,
      "Volume": null,
      "%FromOpen": -4.49
    },
    {
      "Symbol": "RHL",
      "PrevClose": 188.58,
      "OpenPrice": 203.0,
      "%ChangePreOpen": 7.65,
      "Matched": false,
      "LTP": 192.55,
      "Volume": null,
      "%FromOpen": -5.15
    },
    {
      "Symbol": "INDIQUBE",
      "PrevClose": 177.68,
      "OpenPrice": 191.0,
      "%ChangePreOpen": 7.5,
      "Matched": false,
      "LTP": 184.79,
      "Volume": null,
      "%FromOpen": -3.25
    },
    {
      "Symbol": "INNOVANA",
      "PrevClose": 390.65,
      "OpenPrice": 419.7,
      "%ChangePreOpen": 7.44,
      "Matched": false,
      "LTP": 432.85,
      "Volume": null,
      "%FromOpen": 3.13
    },
    {
      "Symbol": "LAXMICOT",
      "PrevClose": 17.0,
      "OpenPrice": 18.25,
      "%ChangePreOpen": 7.35,
      "Matched": false,
      "LTP": 20.15,
      "Volume": null,
      "%FromOpen": 10.41
    },
    {
      "Symbol": "ABMINTLLTD",
      "PrevClose": 52.88,
      "OpenPrice": 56.75,
      "%ChangePreOpen": 7.32,
      "Matched": false,
      "LTP": 59.32,
      "Volume": null,
      "%FromOpen": 4.53
    },
    {
      "Symbol": "RELCHEMQ",
      "PrevClose": 139.33,
      "OpenPrice": 148.7,
      "%ChangePreOpen": 6.73,
      "Matched": false,
      "LTP": 145.87,
      "Volume": null,
      "%FromOpen": -1.9
    },
    {
      "Symbol": "SIKKO",
      "PrevClose": 4.61,
      "OpenPrice": 4.92,
      "%ChangePreOpen": 6.72,
      "Matched": false,
      "LTP": 5.07,
      "Volume": null,
      "%FromOpen": 3.05
    },
    {
      "Symbol": "DAMODARIND",
      "PrevClose": 26.62,
      "OpenPrice": 28.37,
      "%ChangePreOpen": 6.57,
      "Matched": false,
      "LTP": 26.9,
      "Volume": null,
      "%FromOpen": -5.18
    },
    {
      "Symbol": "ELDEHSG",
      "PrevClose": 893.75,
      "OpenPrice": 950.0,
      "%ChangePreOpen": 6.29,
      "Matched": false,
      "LTP": 997.45,
      "Volume": null,
      "%FromOpen": 4.99
    },
    {
      "Symbol": "HEG",
      "PrevClose": 560.7,
      "OpenPrice": 594.0,
      "%ChangePreOpen": 5.94,
      "Matched": false,
      "LTP": 538,
      "Volume": null,
      "%FromOpen": -9.43
    },
    {
      "Symbol": "KRISHIVAL",
      "PrevClose": 350.0,
      "OpenPrice": 369.9,
      "%ChangePreOpen": 5.69,
      "Matched": false,
      "LTP": 356.45,
      "Volume": null,
      "%FromOpen": -3.64
    },
    {
      "Symbol": "DHARAN",
      "PrevClose": 0.19,
      "OpenPrice": 0.2,
      "%ChangePreOpen": 5.26,
      "Matched": false,
      "LTP": 0.19,
      "Volume": null,
      "%FromOpen": -5.0
    },
    {
      "Symbol": "UFLEX",
      "PrevClose": 504.55,
      "OpenPrice": 530.0,
      "%ChangePreOpen": 5.04,
      "Matched": false,
      "LTP": 509.25,
      "Volume": null,
      "%FromOpen": -3.92
    },
    {
      "Symbol": "PKTEA",
      "PrevClose": 738.3,
      "OpenPrice": 775.2,
      "%ChangePreOpen": 5.0,
      "Matched": false,
      "LTP": 775.2,
      "Volume": null,
      "%FromOpen": 0.0
    },
    {
      "Symbol": "UEL",
      "PrevClose": 199.86,
      "OpenPrice": 209.85,
      "%ChangePreOpen": 5.0,
      "Matched": false,
      "LTP": 209.85,
      "Volume": null,
      "%FromOpen": 0.0
    },
    {
      "Symbol": "TECHLABS",
      "PrevClose": 202.05,
      "OpenPrice": 212.15,
      "%ChangePreOpen": 5.0,
      "Matched": false,
      "LTP": 202.8,
      "Volume": null,
      "%FromOpen": -4.41
    },
    {
      "Symbol": "AXISCADES",
      "PrevClose": 1238.5,
      "OpenPrice": 1300.4,
      "%ChangePreOpen": 5.0,
      "Matched": false,
      "LTP": 1300.4,
      "Volume": null,
      "%FromOpen": 0.0
    },
    {
      "Symbol": "PANACHE",
      "PrevClose": 339.4,
      "OpenPrice": 356.35,
      "%ChangePreOpen": 4.99,
      "Matched": false,
      "LTP": 352.5,
      "Volume": null,
      "%FromOpen": -1.08
    },
    {
      "Symbol": "AKIKO",
      "PrevClose": 222.6,
      "OpenPrice": 233.7,
      "%ChangePreOpen": 4.99,
      "Matched": false,
      "LTP": 233.7,
      "Volume": null,
      "%FromOpen": 0.0
    },
    {
      "Symbol": "NIRAJISPAT",
      "PrevClose": 311.46,
      "OpenPrice": 327.0,
      "%ChangePreOpen": 4.99,
      "Matched": false,
      "LTP": 327.03,
      "Volume": null,
      "%FromOpen": 0.01
    },
    {
      "Symbol": "S&SPOWER",
      "PrevClose": 258.55,
      "OpenPrice": 271.45,
      "%ChangePreOpen": 4.99,
      "Matched": false,
      "LTP": null,
      "Volume": null,
      "%FromOpen": null
    },
    {
      "Symbol": "CKKRETAIL",
      "PrevClose": 188.65,
      "OpenPrice": 198.05,
      "%ChangePreOpen": 4.98,
      "Matched": false,
      "LTP": 198.05,
      "Volume": null,
      "%FromOpen": 0.0
    },
    {
      "Symbol": "MANAKALUCO",
      "PrevClose": 31.72,
      "OpenPrice": 33.3,
      "%ChangePreOpen": 4.98,
      "Matched": false,
      "LTP": 33.3,
      "Volume": null,
      "%FromOpen": 0.0
    },
    {
      "Symbol": "ORTINGLOBE",
      "PrevClose": 13.5,
      "OpenPrice": 14.17,
      "%ChangePreOpen": 4.96,
      "Matched": false,
      "LTP": 14.17,
      "Volume": null,
      "%FromOpen": 0.0
    },
    {
      "Symbol": "GLFL",
      "PrevClose": 5.25,
      "OpenPrice": 5.51,
      "%ChangePreOpen": 4.95,
      "Matched": false,
      "LTP": 5.51,
      "Volume": null,
      "%FromOpen": 0.0
    },
    {
      "Symbol": "ONELIFECAP",
      "PrevClose": 13.95,
      "OpenPrice": 14.64,
      "%ChangePreOpen": 4.95,
      "Matched": false,
      "LTP": 14.64,
      "Volume": null,
      "%FromOpen": 0.0
    },
    {
      "Symbol": "PRECISION",
      "PrevClose": 10.15,
      "OpenPrice": 10.65,
      "%ChangePreOpen": 4.93,
      "Matched": false,
      "LTP": 10.65,
      "Volume": null,
      "%FromOpen": 0.0
    },
    {
      "Symbol": "FMNL",
      "PrevClose": 8.52,
      "OpenPrice": 8.94,
      "%ChangePreOpen": 4.93,
      "Matched": false,
      "LTP": 8.49,
      "Volume": null,
      "%FromOpen": -5.03
    },
    {
      "Symbol": "PRAXIS",
      "PrevClose": 8.73,
      "OpenPrice": 9.16,
      "%ChangePreOpen": 4.93,
      "Matched": false,
      "LTP": 8.88,
      "Volume": null,
      "%FromOpen": -3.06
    },
    {
      "Symbol": "KESORAMIND",
      "PrevClose": 9.33,
      "OpenPrice": 9.79,
      "%ChangePreOpen": 4.93,
      "Matched": false,
      "LTP": 9.79,
      "Volume": null,
      "%FromOpen": 0.0
    },
    {
      "Symbol": "SADBHAV",
      "PrevClose": 6.72,
      "OpenPrice": 7.05,
      "%ChangePreOpen": 4.91,
      "Matched": false,
      "LTP": 7.05,
      "Volume": null,
      "%FromOpen": 0.0
    },
    {
      "Symbol": "MTEDUCARE",
      "PrevClose": 1.43,
      "OpenPrice": 1.5,
      "%ChangePreOpen": 4.9,
      "Matched": false,
      "LTP": 1.49,
      "Volume": null,
      "%FromOpen": -0.67
    },
    {
      "Symbol": "ARVINDPORT",
      "PrevClose": 33.8,
      "OpenPrice": 35.45,
      "%ChangePreOpen": 4.88,
      "Matched": false,
      "LTP": 32.25,
      "Volume": null,
      "%FromOpen": -9.03
    },
    {
      "Symbol": "AILIMITED",
      "PrevClose": 24.9,
      "OpenPrice": 26.1,
      "%ChangePreOpen": 4.82,
      "Matched": false,
      "LTP": 26.1,
      "Volume": null,
      "%FromOpen": 0.0
    },
    {
      "Symbol": "KEYFINSERV",
      "PrevClose": 309.15,
      "OpenPrice": 324.0,
      "%ChangePreOpen": 4.8,
      "Matched": false,
      "LTP": 302.5,
      "Volume": null,
      "%FromOpen": -6.64
    },
    {
      "Symbol": "GAYAHWS",
      "PrevClose": 2.5,
      "OpenPrice": 2.62,
      "%ChangePreOpen": 4.8,
      "Matched": false,
      "LTP": 2.62,
      "Volume": null,
      "%FromOpen": 0.0
    },
    {
      "Symbol": "UNITECH",
      "PrevClose": 6.29,
      "OpenPrice": 6.59,
      "%ChangePreOpen": 4.77,
      "Matched": false,
      "LTP": 6.32,
      "Volume": null,
      "%FromOpen": -4.1
    },
    {
      "Symbol": "TREJHARA",
      "PrevClose": 199.51,
      "OpenPrice": 208.7,
      "%ChangePreOpen": 4.61,
      "Matched": false,
      "LTP": 209.48,
      "Volume": null,
      "%FromOpen": 0.37
    },
    {
      "Symbol": "BAWEJA",
      "PrevClose": 33.0,
      "OpenPrice": 34.5,
      "%ChangePreOpen": 4.55,
      "Matched": false,
      "LTP": 31.25,
      "Volume": null,
      "%FromOpen": -9.42
    },
    {
      "Symbol": "TVVISION",
      "PrevClose": 5.94,
      "OpenPrice": 6.21,
      "%ChangePreOpen": 4.55,
      "Matched": false,
      "LTP": 5.97,
      "Volume": null,
      "%FromOpen": -3.86
    },
    {
      "Symbol": "SETUINFRA",
      "PrevClose": 0.44,
      "OpenPrice": 0.46,
      "%ChangePreOpen": 4.55,
      "Matched": false,
      "LTP": 0.42,
      "Volume": null,
      "%FromOpen": -8.7
    },
    {
      "Symbol": "TEXMOPIPES",
      "PrevClose": 48.43,
      "OpenPrice": 50.6,
      "%ChangePreOpen": 4.48,
      "Matched": false,
      "LTP": 53.99,
      "Volume": null,
      "%FromOpen": 6.7
    },
    {
      "Symbol": "GUJRAFFIA",
      "PrevClose": 40.15,
      "OpenPrice": 41.95,
      "%ChangePreOpen": 4.48,
      "Matched": false,
      "LTP": 40,
      "Volume": null,
      "%FromOpen": -4.65
    },
    {
      "Symbol": "KSR",
      "PrevClose": 29.73,
      "OpenPrice": 31.05,
      "%ChangePreOpen": 4.44,
      "Matched": false,
      "LTP": 30.85,
      "Volume": null,
      "%FromOpen": -0.64
    },
    {
      "Symbol": "KMSUGAR",
      "PrevClose": 24.71,
      "OpenPrice": 25.8,
      "%ChangePreOpen": 4.41,
      "Matched": false,
      "LTP": 25.56,
      "Volume": null,
      "%FromOpen": -0.93
    },
    {
      "Symbol": "MAGNUM",
      "PrevClose": 22.97,
      "OpenPrice": 23.98,
      "%ChangePreOpen": 4.4,
      "Matched": false,
      "LTP": 23.01,
      "Volume": null,
      "%FromOpen": -4.05
    },
    {
      "Symbol": "SURAJLTD",
      "PrevClose": 225.09,
      "OpenPrice": 235.0,
      "%ChangePreOpen": 4.4,
      "Matched": false,
      "LTP": 234.87,
      "Volume": null,
      "%FromOpen": -0.06
    },
    {
      "Symbol": "PAVNAIND",
      "PrevClose": 22.8,
      "OpenPrice": 23.8,
      "%ChangePreOpen": 4.39,
      "Matched": false,
      "LTP": 25.8,
      "Volume": null,
      "%FromOpen": 8.4
    },
    {
      "Symbol": "WOMANCART",
      "PrevClose": 167.65,
      "OpenPrice": 175.0,
      "%ChangePreOpen": 4.38,
      "Matched": false,
      "LTP": 179,
      "Volume": null,
      "%FromOpen": 2.29
    },
    {
      "Symbol": "KRITIKA",
      "PrevClose": 6.67,
      "OpenPrice": 6.96,
      "%ChangePreOpen": 4.35,
      "Matched": false,
      "LTP": 6.85,
      "Volume": null,
      "%FromOpen": -1.58
    },
    {
      "Symbol": "HISARMETAL",
      "PrevClose": 172.48,
      "OpenPrice": 179.9,
      "%ChangePreOpen": 4.3,
      "Matched": false,
      "LTP": 174.5,
      "Volume": null,
      "%FromOpen": -3.0
    },
    {
      "Symbol": "BANSWRAS",
      "PrevClose": 117.02,
      "OpenPrice": 122.0,
      "%ChangePreOpen": 4.26,
      "Matched": false,
      "LTP": 123.61,
      "Volume": null,
      "%FromOpen": 1.32
    },
    {
      "Symbol": "IONEXCHANG",
      "PrevClose": 386.8,
      "OpenPrice": 403.25,
      "%ChangePreOpen": 4.25,
      "Matched": false,
      "LTP": 400.85,
      "Volume": null,
      "%FromOpen": -0.6
    },
    {
      "Symbol": "IL&FSENGG",
      "PrevClose": 28.51,
      "OpenPrice": 29.69,
      "%ChangePreOpen": 4.14,
      "Matched": false,
      "LTP": null,
      "Volume": null,
      "%FromOpen": null
    },
    {
      "Symbol": "MOTISONS",
      "PrevClose": 16.09,
      "OpenPrice": 16.75,
      "%ChangePreOpen": 4.1,
      "Matched": false,
      "LTP": 16.49,
      "Volume": null,
      "%FromOpen": -1.55
    },
    {
      "Symbol": "CREATIVEYE",
      "PrevClose": 6.7,
      "OpenPrice": 6.97,
      "%ChangePreOpen": 4.03,
      "Matched": false,
      "LTP": 6.93,
      "Volume": null,
      "%FromOpen": -0.57
    },
    {
      "Symbol": "MADHUCON",
      "PrevClose": 5.24,
      "OpenPrice": 5.45,
      "%ChangePreOpen": 4.01,
      "Matched": false,
      "LTP": 5.29,
      "Volume": null,
      "%FromOpen": -2.94
    },
    {
      "Symbol": "NEPHROPLUS",
      "PrevClose": 535.65,
      "OpenPrice": 557.0,
      "%ChangePreOpen": 3.99,
      "Matched": false,
      "LTP": 562.35,
      "Volume": null,
      "%FromOpen": 0.96
    },
    {
      "Symbol": "CYBERMEDIA",
      "PrevClose": 15.58,
      "OpenPrice": 16.2,
      "%ChangePreOpen": 3.98,
      "Matched": false,
      "LTP": 15.88,
      "Volume": null,
      "%FromOpen": -1.98
    },
    {
      "Symbol": "ARSHIYA",
      "PrevClose": 1.27,
      "OpenPrice": 1.32,
      "%ChangePreOpen": 3.94,
      "Matched": false,
      "LTP": 1.31,
      "Volume": null,
      "%FromOpen": -0.76
    },
    {
      "Symbol": "LAXMIINDIA",
      "PrevClose": 104.93,
      "OpenPrice": 109.0,
      "%ChangePreOpen": 3.88,
      "Matched": false,
      "LTP": 109.23,
      "Volume": null,
      "%FromOpen": 0.21
    },
    {
      "Symbol": "SETCO",
      "PrevClose": 14.23,
      "OpenPrice": 14.78,
      "%ChangePreOpen": 3.87,
      "Matched": false,
      "LTP": 14.5,
      "Volume": null,
      "%FromOpen": -1.89
    },
    {
      "Symbol": "TVSSCS",
      "PrevClose": 107.86,
      "OpenPrice": 112.0,
      "%ChangePreOpen": 3.84,
      "Matched": false,
      "LTP": 121.6,
      "Volume": null,
      "%FromOpen": 8.57
    },
    {
      "Symbol": "TERASOFT",
      "PrevClose": 441.3,
      "OpenPrice": 457.75,
      "%ChangePreOpen": 3.73,
      "Matched": false,
      "LTP": 422.6,
      "Volume": null,
      "%FromOpen": -7.68
    },
    {
      "Symbol": "KRMAYURVED",
      "PrevClose": 194.75,
      "OpenPrice": 202.0,
      "%ChangePreOpen": 3.72,
      "Matched": false,
      "LTP": 211,
      "Volume": null,
      "%FromOpen": 4.46
    },
    {
      "Symbol": "KDL",
      "PrevClose": 144.7,
      "OpenPrice": 150.0,
      "%ChangePreOpen": 3.66,
      "Matched": false,
      "LTP": 148.35,
      "Volume": null,
      "%FromOpen": -1.1
    },
    {
      "Symbol": "SECMARK",
      "PrevClose": 107.95,
      "OpenPrice": 111.9,
      "%ChangePreOpen": 3.66,
      "Matched": false,
      "LTP": 110,
      "Volume": null,
      "%FromOpen": -1.7
    },
    {
      "Symbol": "BCG",
      "PrevClose": 12.04,
      "OpenPrice": 12.48,
      "%ChangePreOpen": 3.65,
      "Matched": false,
      "LTP": 13.59,
      "Volume": null,
      "%FromOpen": 8.89
    },
    {
      "Symbol": "NAGREEKEXP",
      "PrevClose": 27.5,
      "OpenPrice": 28.5,
      "%ChangePreOpen": 3.64,
      "Matched": false,
      "LTP": 27.65,
      "Volume": null,
      "%FromOpen": -2.98
    },
    {
      "Symbol": "KARMAENG",
      "PrevClose": 42.99,
      "OpenPrice": 44.55,
      "%ChangePreOpen": 3.63,
      "Matched": false,
      "LTP": 45.13,
      "Volume": null,
      "%FromOpen": 1.3
    },
    {
      "Symbol": "MSPL",
      "PrevClose": 31.79,
      "OpenPrice": 32.94,
      "%ChangePreOpen": 3.62,
      "Matched": false,
      "LTP": 32.12,
      "Volume": null,
      "%FromOpen": -2.49
    },
    {
      "Symbol": "JHS",
      "PrevClose": 10.79,
      "OpenPrice": 11.18,
      "%ChangePreOpen": 3.61,
      "Matched": false,
      "LTP": 10.95,
      "Volume": null,
      "%FromOpen": -2.06
    },
    {
      "Symbol": "CENTEXT",
      "PrevClose": 21.71,
      "OpenPrice": 22.49,
      "%ChangePreOpen": 3.59,
      "Matched": false,
      "LTP": 21.92,
      "Volume": null,
      "%FromOpen": -2.53
    },
    {
      "Symbol": "GOLDTECH",
      "PrevClose": 45.89,
      "OpenPrice": 47.5,
      "%ChangePreOpen": 3.51,
      "Matched": false,
      "LTP": 45.89,
      "Volume": null,
      "%FromOpen": -3.39
    },
    {
      "Symbol": "SEYAIND",
      "PrevClose": 16.42,
      "OpenPrice": 16.99,
      "%ChangePreOpen": 3.47,
      "Matched": false,
      "LTP": 16.97,
      "Volume": null,
      "%FromOpen": -0.12
    },
    {
      "Symbol": "SEPC",
      "PrevClose": 10.14,
      "OpenPrice": 10.49,
      "%ChangePreOpen": 3.45,
      "Matched": false,
      "LTP": 9.92,
      "Volume": null,
      "%FromOpen": -5.43
    },
    {
      "Symbol": "PAR",
      "PrevClose": 96.67,
      "OpenPrice": 100.0,
      "%ChangePreOpen": 3.44,
      "Matched": false,
      "LTP": 101.55,
      "Volume": null,
      "%FromOpen": 1.55
    },
    {
      "Symbol": "AVROIND",
      "PrevClose": 129.35,
      "OpenPrice": 133.8,
      "%ChangePreOpen": 3.44,
      "Matched": false,
      "LTP": 133.75,
      "Volume": null,
      "%FromOpen": -0.04
    },
    {
      "Symbol": "SAMBHAAV",
      "PrevClose": 7.86,
      "OpenPrice": 8.13,
      "%ChangePreOpen": 3.44,
      "Matched": false,
      "LTP": 7.94,
      "Volume": null,
      "%FromOpen": -2.34
    },
    {
      "Symbol": "HUHTAMAKI",
      "PrevClose": 191.43,
      "OpenPrice": 198.0,
      "%ChangePreOpen": 3.43,
      "Matched": false,
      "LTP": 195.4,
      "Volume": null,
      "%FromOpen": -1.31
    },
    {
      "Symbol": "GSLSU",
      "PrevClose": 89.32,
      "OpenPrice": 92.38,
      "%ChangePreOpen": 3.43,
      "Matched": false,
      "LTP": 88.33,
      "Volume": null,
      "%FromOpen": -4.38
    },
    {
      "Symbol": "ALLCARGO",
      "PrevClose": 9.99,
      "OpenPrice": 10.33,
      "%ChangePreOpen": 3.4,
      "Matched": false,
      "LTP": 9.99,
      "Volume": null,
      "%FromOpen": -3.29
    },
    {
      "Symbol": "ATL",
      "PrevClose": 25.15,
      "OpenPrice": 26.0,
      "%ChangePreOpen": 3.38,
      "Matched": false,
      "LTP": 27.08,
      "Volume": null,
      "%FromOpen": 4.15
    },
    {
      "Symbol": "IITL",
      "PrevClose": 140.27,
      "OpenPrice": 145.0,
      "%ChangePreOpen": 3.37,
      "Matched": false,
      "LTP": 141.24,
      "Volume": null,
      "%FromOpen": -2.59
    },
    {
      "Symbol": "CCHHL",
      "PrevClose": 13.88,
      "OpenPrice": 14.34,
      "%ChangePreOpen": 3.31,
      "Matched": false,
      "LTP": 13.84,
      "Volume": null,
      "%FromOpen": -3.49
    },
    {
      "Symbol": "PVSL",
      "PrevClose": 121.01,
      "OpenPrice": 125.0,
      "%ChangePreOpen": 3.3,
      "Matched": false,
      "LTP": 117.15,
      "Volume": null,
      "%FromOpen": -6.28
    },
    {
      "Symbol": "LAL",
      "PrevClose": 8.22,
      "OpenPrice": 8.49,
      "%ChangePreOpen": 3.28,
      "Matched": false,
      "LTP": 8.35,
      "Volume": null,
      "%FromOpen": -1.65
    },
    {
      "Symbol": "TMCV",
      "PrevClose": 472.55,
      "OpenPrice": 488.0,
      "%ChangePreOpen": 3.27,
      "Matched": false,
      "LTP": 485.6,
      "Volume": null,
      "%FromOpen": -0.49
    },
    {
      "Symbol": "UMESLTD",
      "PrevClose": 4.68,
      "OpenPrice": 4.83,
      "%ChangePreOpen": 3.21,
      "Matched": false,
      "LTP": 4.63,
      "Volume": null,
      "%FromOpen": -4.14
    },
    {
      "Symbol": "UNIVASTU",
      "PrevClose": 67.4,
      "OpenPrice": 69.5,
      "%ChangePreOpen": 3.12,
      "Matched": false,
      "LTP": 66.68,
      "Volume": null,
      "%FromOpen": -4.06
    },
    {
      "Symbol": "RKDL",
      "PrevClose": 20.37,
      "OpenPrice": 21.0,
      "%ChangePreOpen": 3.09,
      "Matched": false,
      "LTP": 20.31,
      "Volume": null,
      "%FromOpen": -3.29
    },
    {
      "Symbol": "SIGMA",
      "PrevClose": 50.11,
      "OpenPrice": 51.66,
      "%ChangePreOpen": 3.09,
      "Matched": false,
      "LTP": 50.1,
      "Volume": null,
      "%FromOpen": -3.02
    },
    {
      "Symbol": "SHANTI",
      "PrevClose": 7.12,
      "OpenPrice": 7.34,
      "%ChangePreOpen": 3.09,
      "Matched": false,
      "LTP": 7.13,
      "Volume": null,
      "%FromOpen": -2.86
    },
    {
      "Symbol": "NACLIND",
      "PrevClose": 144.98,
      "OpenPrice": 149.45,
      "%ChangePreOpen": 3.08,
      "Matched": false,
      "LTP": 150.92,
      "Volume": null,
      "%FromOpen": 0.98
    },
    {
      "Symbol": "NDTV",
      "PrevClose": 87.34,
      "OpenPrice": 90.0,
      "%ChangePreOpen": 3.05,
      "Matched": false,
      "LTP": 87.82,
      "Volume": null,
      "%FromOpen": -2.42
    },
    {
      "Symbol": "CTE",
      "PrevClose": 35.62,
      "OpenPrice": 36.7,
      "%ChangePreOpen": 3.03,
      "Matched": false,
      "LTP": 36.38,
      "Volume": null,
      "%FromOpen": -0.87
    },
    {
      "Symbol": "KOTARISUG",
      "PrevClose": 28.03,
      "OpenPrice": 28.88,
      "%ChangePreOpen": 3.03,
      "Matched": false,
      "LTP": 28.1,
      "Volume": null,
      "%FromOpen": -2.7
    },
    {
      "Symbol": "FILATFASH",
      "PrevClose": 0.33,
      "OpenPrice": 0.34,
      "%ChangePreOpen": 3.03,
      "Matched": false,
      "LTP": 0.34,
      "Volume": null,
      "%FromOpen": 0.0
    },
    {
      "Symbol": "PACEDIGITK",
      "PrevClose": 194.54,
      "OpenPrice": 200.39,
      "%ChangePreOpen": 3.01,
      "Matched": false,
      "LTP": 196.5,
      "Volume": null,
      "%FromOpen": -1.94
    },
    {
      "Symbol": "MVGJL",
      "PrevClose": 191.24,
      "OpenPrice": 197.0,
      "%ChangePreOpen": 3.01,
      "Matched": false,
      "LTP": 186.05,
      "Volume": null,
      "%FromOpen": -5.56
    },
    {
      "Symbol": "PHANTOMFX",
      "PrevClose": 233.7,
      "OpenPrice": 240.7,
      "%ChangePreOpen": 3.0,
      "Matched": false,
      "LTP": 228.15,
      "Volume": null,
      "%FromOpen": -5.21
    },
    {
      "Symbol": "ARMOUR",
      "PrevClose": 28.35,
      "OpenPrice": 29.2,
      "%ChangePreOpen": 3.0,
      "Matched": false,
      "LTP": 28,
      "Volume": null,
      "%FromOpen": -4.11
    },
    {
      "Symbol": "AHLEAST",
      "PrevClose": 150.4,
      "OpenPrice": 154.9,
      "%ChangePreOpen": 2.99,
      "Matched": false,
      "LTP": 149,
      "Volume": null,
      "%FromOpen": -3.81
    },
    {
      "Symbol": "CAPTRUST",
      "PrevClose": 14.81,
      "OpenPrice": 15.25,
      "%ChangePreOpen": 2.97,
      "Matched": false,
      "LTP": 14.98,
      "Volume": null,
      "%FromOpen": -1.77
    },
    {
      "Symbol": "KEEPLEARN",
      "PrevClose": 2.03,
      "OpenPrice": 2.09,
      "%ChangePreOpen": 2.96,
      "Matched": false,
      "LTP": 2.02,
      "Volume": null,
      "%FromOpen": -3.35
    },
    {
      "Symbol": "AVANA",
      "PrevClose": 72.75,
      "OpenPrice": 74.9,
      "%ChangePreOpen": 2.96,
      "Matched": false,
      "LTP": 68,
      "Volume": null,
      "%FromOpen": -9.21
    },
    {
      "Symbol": "PRESSTONIC",
      "PrevClose": 62.65,
      "OpenPrice": 64.5,
      "%ChangePreOpen": 2.95,
      "Matched": false,
      "LTP": 65,
      "Volume": null,
      "%FromOpen": 0.78
    },
    {
      "Symbol": "SANWARIA",
      "PrevClose": 0.34,
      "OpenPrice": 0.35,
      "%ChangePreOpen": 2.94,
      "Matched": false,
      "LTP": 0.33,
      "Volume": null,
      "%FromOpen": -5.71
    },
    {
      "Symbol": "SUBEXLTD",
      "PrevClose": 10.69,
      "OpenPrice": 11.0,
      "%ChangePreOpen": 2.9,
      "Matched": false,
      "LTP": 10.95,
      "Volume": null,
      "%FromOpen": -0.45
    },
    {
      "Symbol": "FOCUS",
      "PrevClose": 66.04,
      "OpenPrice": 67.94,
      "%ChangePreOpen": 2.88,
      "Matched": false,
      "LTP": 65.1,
      "Volume": null,
      "%FromOpen": -4.18
    },
    {
      "Symbol": "EICHERMOT",
      "PrevClose": 7296.0,
      "OpenPrice": 7505.0,
      "%ChangePreOpen": 2.86,
      "Matched": false,
      "LTP": 7770,
      "Volume": null,
      "%FromOpen": 3.53
    },
    {
      "Symbol": "JPASSOCIAT",
      "PrevClose": 3.2,
      "OpenPrice": 3.29,
      "%ChangePreOpen": 2.81,
      "Matched": false,
      "LTP": 3.33,
      "Volume": null,
      "%FromOpen": 1.22
    },
    {
      "Symbol": "KAVDEFENCE",
      "PrevClose": 75.68,
      "OpenPrice": 77.8,
      "%ChangePreOpen": 2.8,
      "Matched": false,
      "LTP": 83.24,
      "Volume": null,
      "%FromOpen": 6.99
    },
    {
      "Symbol": "SANSERA",
      "PrevClose": 2035.0,
      "OpenPrice": 2092.0,
      "%ChangePreOpen": 2.8,
      "Matched": false,
      "LTP": 2110,
      "Volume": null,
      "%FromOpen": 0.86
    },
    {
      "Symbol": "JUBLFOOD",
      "PrevClose": 554.45,
      "OpenPrice": 570.0,
      "%ChangePreOpen": 2.8,
      "Matched": false,
      "LTP": 548.35,
      "Volume": null,
      "%FromOpen": -3.8
    },
    {
      "Symbol": "SITINET",
      "PrevClose": 0.36,
      "OpenPrice": 0.37,
      "%ChangePreOpen": 2.78,
      "Matched": false,
      "LTP": 0.37,
      "Volume": null,
      "%FromOpen": 0.0
    },
    {
      "Symbol": "MONEYBOXX",
      "PrevClose": 59.85,
      "OpenPrice": 61.5,
      "%ChangePreOpen": 2.76,
      "Matched": false,
      "LTP": 60.2,
      "Volume": null,
      "%FromOpen": -2.11
    },
    {
      "Symbol": "EUROBOND",
      "PrevClose": 179.55,
      "OpenPrice": 184.5,
      "%ChangePreOpen": 2.76,
      "Matched": false,
      "LTP": 180.31,
      "Volume": null,
      "%FromOpen": -2.27
    },
    {
      "Symbol": "BIRLACABLE",
      "PrevClose": 152.76,
      "OpenPrice": 156.98,
      "%ChangePreOpen": 2.76,
      "Matched": false,
      "LTP": 151.3,
      "Volume": null,
      "%FromOpen": -3.62
    },
    {
      "Symbol": "RSYSTEMS",
      "PrevClose": 345.5,
      "OpenPrice": 355.0,
      "%ChangePreOpen": 2.75,
      "Matched": false,
      "LTP": 358.4,
      "Volume": null,
      "%FromOpen": 0.96
    },
    {
      "Symbol": "LOVABLE",
      "PrevClose": 79.33,
      "OpenPrice": 81.5,
      "%ChangePreOpen": 2.74,
      "Matched": false,
      "LTP": 79.99,
      "Volume": null,
      "%FromOpen": -1.85
    },
    {
      "Symbol": "SOFTTECH",
      "PrevClose": 306.25,
      "OpenPrice": 314.65,
      "%ChangePreOpen": 2.74,
      "Matched": false,
      "LTP": 307,
      "Volume": null,
      "%FromOpen": -2.43
    },
    {
      "Symbol": "AXITA",
      "PrevClose": 10.36,
      "OpenPrice": 10.64,
      "%ChangePreOpen": 2.7,
      "Matched": false,
      "LTP": 10.61,
      "Volume": null,
      "%FromOpen": -0.28
    },
    {
      "Symbol": "ASIANHOTNR",
      "PrevClose": 278.5,
      "OpenPrice": 286.0,
      "%ChangePreOpen": 2.69,
      "Matched": false,
      "LTP": 277.65,
      "Volume": null,
      "%FromOpen": -2.92
    },
    {
      "Symbol": "GANGAFORGE",
      "PrevClose": 3.36,
      "OpenPrice": 3.45,
      "%ChangePreOpen": 2.68,
      "Matched": false,
      "LTP": 3.38,
      "Volume": null,
      "%FromOpen": -2.03
    },
    {
      "Symbol": "SUMEETINDS",
      "PrevClose": 27.23,
      "OpenPrice": 27.96,
      "%ChangePreOpen": 2.68,
      "Matched": false,
      "LTP": 26.82,
      "Volume": null,
      "%FromOpen": -4.08
    },
    {
      "Symbol": "MODINATUR",
      "PrevClose": 344.9,
      "OpenPrice": 354.0,
      "%ChangePreOpen": 2.64,
      "Matched": false,
      "LTP": 349.65,
      "Volume": null,
      "%FromOpen": -1.23
    },
    {
      "Symbol": "ODIGMA",
      "PrevClose": 30.58,
      "OpenPrice": 31.38,
      "%ChangePreOpen": 2.62,
      "Matched": false,
      "LTP": 30.5,
      "Volume": null,
      "%FromOpen": -2.8
    },
    {
      "Symbol": "AMJLAND",
      "PrevClose": 42.2,
      "OpenPrice": 43.3,
      "%ChangePreOpen": 2.61,
      "Matched": false,
      "LTP": 41.1,
      "Volume": null,
      "%FromOpen": -5.08
    },
    {
      "Symbol": "TOTAL",
      "PrevClose": 65.01,
      "OpenPrice": 66.7,
      "%ChangePreOpen": 2.6,
      "Matched": false,
      "LTP": 66,
      "Volume": null,
      "%FromOpen": -1.05
    },
    {
      "Symbol": "BALPHARMA",
      "PrevClose": 70.09,
      "OpenPrice": 71.9,
      "%ChangePreOpen": 2.58,
      "Matched": false,
      "LTP": 70.79,
      "Volume": null,
      "%FromOpen": -1.54
    },
    {
      "Symbol": "TREEHOUSE",
      "PrevClose": 7.75,
      "OpenPrice": 7.95,
      "%ChangePreOpen": 2.58,
      "Matched": false,
      "LTP": 7.83,
      "Volume": null,
      "%FromOpen": -1.51
    },
    {
      "Symbol": "APOLLOHOSP",
      "PrevClose": 7219.0,
      "OpenPrice": 7405.0,
      "%ChangePreOpen": 2.58,
      "Matched": false,
      "LTP": 7542.5,
      "Volume": null,
      "%FromOpen": 1.86
    },
    {
      "Symbol": "KKCL",
      "PrevClose": 506.95,
      "OpenPrice": 520.0,
      "%ChangePreOpen": 2.57,
      "Matched": false,
      "LTP": 547.65,
      "Volume": null,
      "%FromOpen": 5.32
    },
    {
      "Symbol": "BHANDARI",
      "PrevClose": 4.28,
      "OpenPrice": 4.39,
      "%ChangePreOpen": 2.57,
      "Matched": false,
      "LTP": 4.28,
      "Volume": null,
      "%FromOpen": -2.51
    },
    {
      "Symbol": "SHRENIK",
      "PrevClose": 0.39,
      "OpenPrice": 0.4,
      "%ChangePreOpen": 2.56,
      "Matched": false,
      "LTP": 0.4,
      "Volume": null,
      "%FromOpen": 0.0
    },
    {
      "Symbol": "OSWALSEEDS",
      "PrevClose": 14.13,
      "OpenPrice": 14.49,
      "%ChangePreOpen": 2.55,
      "Matched": false,
      "LTP": 14.1,
      "Volume": null,
      "%FromOpen": -2.69
    },
    {
      "Symbol": "DELPHIFX",
      "PrevClose": 230.06,
      "OpenPrice": 235.9,
      "%ChangePreOpen": 2.54,
      "Matched": false,
      "LTP": 233.67,
      "Volume": null,
      "%FromOpen": -0.95
    },
    {
      "Symbol": "AKASH",
      "PrevClose": 24.81,
      "OpenPrice": 25.44,
      "%ChangePreOpen": 2.54,
      "Matched": false,
      "LTP": 24.61,
      "Volume": null,
      "%FromOpen": -3.26
    },
    {
      "Symbol": "SILKFLEX",
      "PrevClose": 122.9,
      "OpenPrice": 126.0,
      "%ChangePreOpen": 2.52,
      "Matched": false,
      "LTP": 118.25,
      "Volume": null,
      "%FromOpen": -6.15
    },
    {
      "Symbol": "BIRLANU",
      "PrevClose": 1814.5,
      "OpenPrice": 1860.0,
      "%ChangePreOpen": 2.51,
      "Matched": false,
      "LTP": 1790,
      "Volume": null,
      "%FromOpen": -3.76
    },
    {
      "Symbol": "SMLT",
      "PrevClose": 79.68,
      "OpenPrice": 81.68,
      "%ChangePreOpen": 2.51,
      "Matched": false,
      "LTP": 92.25,
      "Volume": null,
      "%FromOpen": 12.94
    },
    {
      "Symbol": "SHEKHAWATI",
      "PrevClose": 14.74,
      "OpenPrice": 15.1,
      "%ChangePreOpen": 2.44,
      "Matched": false,
      "LTP": 14.72,
      "Volume": null,
      "%FromOpen": -2.52
    },
    {
      "Symbol": "HARRMALAYA",
      "PrevClose": 159.53,
      "OpenPrice": 163.4,
      "%ChangePreOpen": 2.43,
      "Matched": false,
      "LTP": 162,
      "Volume": null,
      "%FromOpen": -0.86
    },
    {
      "Symbol": "PARASPETRO",
      "PrevClose": 2.47,
      "OpenPrice": 2.53,
      "%ChangePreOpen": 2.43,
      "Matched": false,
      "LTP": 2.59,
      "Volume": null,
      "%FromOpen": 2.37
    },
    {
      "Symbol": "CYBERTECH",
      "PrevClose": 137.65,
      "OpenPrice": 141.0,
      "%ChangePreOpen": 2.43,
      "Matched": false,
      "LTP": 139.52,
      "Volume": null,
      "%FromOpen": -1.05
    },
    {
      "Symbol": "TIGERLOGS",
      "PrevClose": 34.03,
      "OpenPrice": 34.85,
      "%ChangePreOpen": 2.41,
      "Matched": false,
      "LTP": 34.11,
      "Volume": null,
      "%FromOpen": -2.12
    },
    {
      "Symbol": "BAGFILMS",
      "PrevClose": 5.83,
      "OpenPrice": 5.97,
      "%ChangePreOpen": 2.4,
      "Matched": false,
      "LTP": 5.86,
      "Volume": null,
      "%FromOpen": -1.84
    },
    {
      "Symbol": "MCLEODRUSS",
      "PrevClose": 46.87,
      "OpenPrice": 47.99,
      "%ChangePreOpen": 2.39,
      "Matched": false,
      "LTP": 46.68,
      "Volume": null,
      "%FromOpen": -2.73
    },
    {
      "Symbol": "JMA",
      "PrevClose": 79.1,
      "OpenPrice": 80.99,
      "%ChangePreOpen": 2.39,
      "Matched": false,
      "LTP": 78.11,
      "Volume": null,
      "%FromOpen": -3.56
    },
    {
      "Symbol": "KRIDHANINF",
      "PrevClose": 3.79,
      "OpenPrice": 3.88,
      "%ChangePreOpen": 2.37,
      "Matched": false,
      "LTP": 3.84,
      "Volume": null,
      "%FromOpen": -1.03
    },
    {
      "Symbol": "AARVI",
      "PrevClose": 130.92,
      "OpenPrice": 133.99,
      "%ChangePreOpen": 2.34,
      "Matched": false,
      "LTP": 131.38,
      "Volume": null,
      "%FromOpen": -1.95
    },
    {
      "Symbol": "ARIES",
      "PrevClose": 329.9,
      "OpenPrice": 337.6,
      "%ChangePreOpen": 2.33,
      "Matched": false,
      "LTP": 328.65,
      "Volume": null,
      "%FromOpen": -2.65
    },
    {
      "Symbol": "ASMS",
      "PrevClose": 12.05,
      "OpenPrice": 12.33,
      "%ChangePreOpen": 2.32,
      "Matched": false,
      "LTP": 12.05,
      "Volume": null,
      "%FromOpen": -2.27
    },
    {
      "Symbol": "DIGIDRIVE",
      "PrevClose": 23.34,
      "OpenPrice": 23.88,
      "%ChangePreOpen": 2.31,
      "Matched": false,
      "LTP": 23.32,
      "Volume": null,
      "%FromOpen": -2.35
    },
    {
      "Symbol": "BAFNAPH",
      "PrevClose": 127.89,
      "OpenPrice": 130.85,
      "%ChangePreOpen": 2.31,
      "Matched": false,
      "LTP": 125,
      "Volume": null,
      "%FromOpen": -4.47
    },
    {
      "Symbol": "DHUNINV",
      "PrevClose": 1017.6,
      "OpenPrice": 1041.0,
      "%ChangePreOpen": 2.3,
      "Matched": false,
      "LTP": 1018,
      "Volume": null,
      "%FromOpen": -2.21
    },
    {
      "Symbol": "ADVAIT",
      "PrevClose": 1633.1,
      "OpenPrice": 1670.0,
      "%ChangePreOpen": 2.26,
      "Matched": false,
      "LTP": 1660.9,
      "Volume": null,
      "%FromOpen": -0.54
    },
    {
      "Symbol": "JUNIPER",
      "PrevClose": 254.8,
      "OpenPrice": 260.5,
      "%ChangePreOpen": 2.24,
      "Matched": false,
      "LTP": 266.52,
      "Volume": null,
      "%FromOpen": 2.31
    },
    {
      "Symbol": "HIRECT",
      "PrevClose": 1418.3,
      "OpenPrice": 1449.9,
      "%ChangePreOpen": 2.23,
      "Matched": false,
      "LTP": 1414.1,
      "Volume": null,
      "%FromOpen": -2.47
    },
    {
      "Symbol": "ARROWGREEN",
      "PrevClose": 445.0,
      "OpenPrice": 454.9,
      "%ChangePreOpen": 2.22,
      "Matched": false,
      "LTP": 447.9,
      "Volume": null,
      "%FromOpen": -1.54
    },
    {
      "Symbol": "FEL",
      "PrevClose": 0.45,
      "OpenPrice": 0.46,
      "%ChangePreOpen": 2.22,
      "Matched": false,
      "LTP": 0.45,
      "Volume": null,
      "%FromOpen": -2.17
    },
    {
      "Symbol": "RADAAN",
      "PrevClose": 3.18,
      "OpenPrice": 3.25,
      "%ChangePreOpen": 2.2,
      "Matched": false,
      "LTP": 3.25,
      "Volume": null,
      "%FromOpen": 0.0
    },
    {
      "Symbol": "UBL",
      "PrevClose": 1619.7,
      "OpenPrice": 1655.0,
      "%ChangePreOpen": 2.18,
      "Matched": false,
      "LTP": 1627.1,
      "Volume": null,
      "%FromOpen": -1.69
    },
    {
      "Symbol": "RHFL",
      "PrevClose": 2.76,
      "OpenPrice": 2.82,
      "%ChangePreOpen": 2.17,
      "Matched": false,
      "LTP": 2.79,
      "Volume": null,
      "%FromOpen": -1.06
    },
    {
      "Symbol": "MKPL",
      "PrevClose": 5.52,
      "OpenPrice": 5.64,
      "%ChangePreOpen": 2.17,
      "Matched": false,
      "LTP": 5.65,
      "Volume": null,
      "%FromOpen": 0.18
    },
    {
      "Symbol": "UNIDT",
      "PrevClose": 185.85,
      "OpenPrice": 189.85,
      "%ChangePreOpen": 2.15,
      "Matched": false,
      "LTP": 185.85,
      "Volume": null,
      "%FromOpen": -2.11
    },
    {
      "Symbol": "BRITANNIA",
      "PrevClose": 5873.5,
      "OpenPrice": 6000.0,
      "%ChangePreOpen": 2.15,
      "Matched": false,
      "LTP": 6076,
      "Volume": null,
      "%FromOpen": 1.27
    },
    {
      "Symbol": "AVG",
      "PrevClose": 151.75,
      "OpenPrice": 155.0,
      "%ChangePreOpen": 2.14,
      "Matched": false,
      "LTP": 150,
      "Volume": null,
      "%FromOpen": -3.23
    },
    {
      "Symbol": "SPCENET",
      "PrevClose": 5.14,
      "OpenPrice": 5.25,
      "%ChangePreOpen": 2.14,
      "Matched": false,
      "LTP": 5.34,
      "Volume": null,
      "%FromOpen": 1.71
    },
    {
      "Symbol": "ANTGRAPHIC",
      "PrevClose": 0.94,
      "OpenPrice": 0.96,
      "%ChangePreOpen": 2.13,
      "Matched": false,
      "LTP": 0.95,
      "Volume": null,
      "%FromOpen": -1.04
    },
    {
      "Symbol": "VAISHALI",
      "PrevClose": 8.07,
      "OpenPrice": 8.24,
      "%ChangePreOpen": 2.11,
      "Matched": false,
      "LTP": 8.12,
      "Volume": null,
      "%FromOpen": -1.46
    },
    {
      "Symbol": "KELLTONTEC",
      "PrevClose": 17.73,
      "OpenPrice": 18.1,
      "%ChangePreOpen": 2.09,
      "Matched": false,
      "LTP": 17.95,
      "Volume": null,
      "%FromOpen": -0.83
    },
    {
      "Symbol": "UGROCAP",
      "PrevClose": 135.22,
      "OpenPrice": 138.0,
      "%ChangePreOpen": 2.06,
      "Matched": false,
      "LTP": 135.79,
      "Volume": null,
      "%FromOpen": -1.6
    },
    {
      "Symbol": "CEREBRAINT",
      "PrevClose": 5.33,
      "OpenPrice": 5.44,
      "%ChangePreOpen": 2.06,
      "Matched": false,
      "LTP": 5.39,
      "Volume": null,
      "%FromOpen": -0.92
    },
    {
      "Symbol": "K2INFRA",
      "PrevClose": 60.95,
      "OpenPrice": 62.2,
      "%ChangePreOpen": 2.05,
      "Matched": false,
      "LTP": 62.1,
      "Volume": null,
      "%FromOpen": -0.16
    },
    {
      "Symbol": "SMLMAH",
      "PrevClose": 4330.7,
      "OpenPrice": 4419.0,
      "%ChangePreOpen": 2.04,
      "Matched": false,
      "LTP": 4448.8,
      "Volume": null,
      "%FromOpen": 0.67
    },
    {
      "Symbol": "MFML",
      "PrevClose": 25.95,
      "OpenPrice": 26.48,
      "%ChangePreOpen": 2.04,
      "Matched": false,
      "LTP": 25.11,
      "Volume": null,
      "%FromOpen": -5.17
    },
    {
      "Symbol": "AFFLE",
      "PrevClose": 1664.1,
      "OpenPrice": 1698.0,
      "%ChangePreOpen": 2.04,
      "Matched": false,
      "LTP": 1647.4,
      "Volume": null,
      "%FromOpen": -2.98
    },
    {
      "Symbol": "VLEGOV",
      "PrevClose": 13.72,
      "OpenPrice": 14.0,
      "%ChangePreOpen": 2.04,
      "Matched": false,
      "LTP": 13.69,
      "Volume": null,
      "%FromOpen": -2.21
    },
    {
      "Symbol": "GENUSPAPER",
      "PrevClose": 12.32,
      "OpenPrice": 12.57,
      "%ChangePreOpen": 2.03,
      "Matched": false,
      "LTP": 12.69,
      "Volume": null,
      "%FromOpen": 0.95
    },
    {
      "Symbol": "NOIDATOLL",
      "PrevClose": 3.99,
      "OpenPrice": 4.07,
      "%ChangePreOpen": 2.01,
      "Matched": false,
      "LTP": 4.13,
      "Volume": null,
      "%FromOpen": 1.47
    },
    {
      "Symbol": "DECCANCE",
      "PrevClose": 712.4,
      "OpenPrice": 726.75,
      "%ChangePreOpen": 2.01,
      "Matched": false,
      "LTP": 726.55,
      "Volume": null,
      "%FromOpen": -0.03
    },
    {
      "Symbol": "ZODIACLOTH",
      "PrevClose": 88.22,
      "OpenPrice": 89.99,
      "%ChangePreOpen": 2.01,
      "Matched": false,
      "LTP": 87.78,
      "Volume": null,
      "%FromOpen": -2.46
    },
    {
      "Symbol": "TTL",
      "PrevClose": 9.51,
      "OpenPrice": 9.7,
      "%ChangePreOpen": 2.0,
      "Matched": false,
      "LTP": 9.63,
      "Volume": null,
      "%FromOpen": -0.72
    },
    {
      "Symbol": "RAJESHEXPO",
      "PrevClose": 188.63,
      "OpenPrice": 192.4,
      "%ChangePreOpen": 2.0,
      "Matched": false,
      "LTP": 184.99,
      "Volume": null,
      "%FromOpen": -3.85
    },
    {
      "Symbol": "MAZDA",
      "PrevClose": 215.98,
      "OpenPrice": 220.29,
      "%ChangePreOpen": 2.0,
      "Matched": false,
      "LTP": 215,
      "Volume": null,
      "%FromOpen": -2.4
    },
    {
      "Symbol": "GATECHDVR",
      "PrevClose": 0.5,
      "OpenPrice": 0.51,
      "%ChangePreOpen": 2.0,
      "Matched": false,
      "LTP": 0.5,
      "Volume": null,
      "%FromOpen": -1.96
    },
    {
      "Symbol": "CIFL",
      "PrevClose": 32.17,
      "OpenPrice": 32.81,
      "%ChangePreOpen": 1.99,
      "Matched": false,
      "LTP": 31.98,
      "Volume": null,
      "%FromOpen": -2.53
    },
    {
      "Symbol": "PREMIERPOL",
      "PrevClose": 53.43,
      "OpenPrice": 54.49,
      "%ChangePreOpen": 1.98,
      "Matched": false,
      "LTP": 54.89,
      "Volume": null,
      "%FromOpen": 0.73
    },
    {
      "Symbol": "DBL",
      "PrevClose": 469.2,
      "OpenPrice": 478.5,
      "%ChangePreOpen": 1.98,
      "Matched": false,
      "LTP": 473.45,
      "Volume": null,
      "%FromOpen": -1.06
    },
    {
      "Symbol": "MANUGRAPH",
      "PrevClose": 17.64,
      "OpenPrice": 17.99,
      "%ChangePreOpen": 1.98,
      "Matched": false,
      "LTP": 18.03,
      "Volume": null,
      "%FromOpen": 0.22
    },
    {
      "Symbol": "KERNEX",
      "PrevClose": 1196.6,
      "OpenPrice": 1220.0,
      "%ChangePreOpen": 1.96,
      "Matched": false,
      "LTP": 1239.2,
      "Volume": null,
      "%FromOpen": 1.57
    }
  ]
}